{
    "thread": {
        "uuid": "9a6246d87e038c84796f38d9b715968ea3ef2070",
        "url": "https://americanmilitarynews.com/2024/11/pa-supreme-court-rejects-phillys-latest-attempt-to-pass-its-own-gun-laws",
        "site_full": "americanmilitarynews.com",
        "site": "americanmilitarynews.com",
        "site_section": "https://news.whatfinger.com/feed",
        "site_categories": [
            "media",
            "jobs",
            "us_military"
        ],
        "section_title": "Whatfinger Wire News",
        "title": "Pa. Supreme Court rejects Philly’s latest attempt to pass its own gun laws",
        "title_full": "Pa. Supreme Court rejects Philly’s latest attempt to pass its own gun laws",
        "published": "2024-11-23T00:03:00.000+02:00",
        "replies_count": 0,
        "participants_count": 1,
        "site_type": "news",
        "country": "US",
        "main_image": "https://americanmilitarynews.com/wp-content/uploads/US-NEWS-PHILLY-GUN-LAWS-PH-scaled.jpg",
        "performance_score": 0,
        "domain_rank": 20925,
        "domain_rank_updated": "2024-11-18T23:00:00.000+02:00",
        "social": {
            "facebook": {
                "likes": 0,
                "comments": 0,
                "shares": 0
            },
            "vk": {
                "shares": 0
            }
        }
    },
    "uuid": "9a6246d87e038c84796f38d9b715968ea3ef2070",
    "url": "https://americanmilitarynews.com/2024/11/pa-supreme-court-rejects-phillys-latest-attempt-to-pass-its-own-gun-laws",
    "ord_in_thread": 0,
    "parent_url": null,
    "author": "Chris Palmer - The Philadelphia Inquirer, Gillian McGoldrick - The Philadelphia Inquirer",
    "published": "2024-11-23T00:03:00.000+02:00",
    "title": "Pa. Supreme Court rejects Philly’s latest attempt to pass its own gun laws",
    "text": "Philadelphia's effort to enact its own gun laws was rejected once again by the Pennsylvania Supreme Court. (Steven M. Falk/The Philadelphia Inquirer/TNS) November 22, 2024 Chris Palmer - The Philadelphia Inquirer and Gillian McGoldrick - The Philadelphia Inquirer\nFacebook\nTwitter\nLinkedin\nEmail\nThe Pennsylvania Supreme Court on Wednesday rejected another attempt by Philadelphia officials to overturn a long-standing state provision that prevents the city from enacting its own gun laws.\nIn a 6-0 decision , the high court ruled that the city’s arguments had fallen “woefully short” of the standard needed for a legal victory — and said that despite the pleas of city attorneys and those impacted by gun violence, they had not proven that the current prohibition against local gun ordinances was the cause of Philadelphia’s gun violence.\nCity officials for years have attempted to overcome the legal hurdle known as preemption, which bans municipalities from passing gun control measures that are stricter than state laws. Mayors and City Council members have nonetheless sought to ban assault-style weapons, limit handgun purchases and prohibit guns in parks and at recreation centers — only for the courts to rule that the provisions were prohibited.\nIn this case, filed in 2020 by Mayor Jim Kenney’s administration, attorneys representing the city and a group of people affected by gun violence had argued in part that preemption violated Philadelphians’ constitutional rights to life and liberty — and that the General Assembly had caused the danger by failing to enact new statewide laws on its own.\nCity officials said that if allowed, they would enact new statutes intended to make it harder for people to obtain weapons for criminal use — such as requiring a permit to purchase guns in the city, or limiting the number of guns a person could buy in the city limits within a certain time frame.\nBut Justice P. Kevin Brobson, writing for the court, said it was “wholly insufficient” to argue that an individual’s rights were tied to a municipality’s ability to pass local laws. And he said the city had failed to prove its assertion that the General Assembly was guilty of “state created danger” because a variety of factors beyond policy decisions contribute to gun violence.\nCity officials did not immediately respond to requests for comment.\nAdam Garber, executive director of the gun violence prevention advocacy group CeaseFire PA — which joined the city in its suit — said in a statement that the decision leaves “local governments handcuffed” and prevents them from addressing the leading cause of death among Black men and youth in the state.\nBut Garber said his organization is hopeful about the prospect of success for other ongoing firearm lawsuits, including Philadelphia’s effort to enforce reporting of lost or stolen guns. Based on the court’s decision, he also urged the General Assembly — made up of the GOP-controlled Senate and a narrow Democratic majority in the House — to take action “before more lives are lost.”\nOne thing has changed significantly since the city filed its suit in 2020: Philadelphia’s rate of gun violence has been cut nearly in half.\nMore than 430 people had been killed in homicides through Nov. 20, 2020, police statistics show, the vast majority by gun.\nThis year, through the same date, the statistics show, 228 people have been slain.\n___\n© 2024 The Philadelphia Inquirer\nDistributed by Tribune Content Agency, LLC.\nSubscribe to our newsletter and breaking news alerts * indicates required Email Address * First Name",
    "highlightText": "",
    "highlightTitle": "",
    "highlightThreadTitle": "",
    "language": "english",
    "sentiment": "negative",
    "categories": [
        "Politics",
        "Crime, Law and Justice"
    ],
    "ai_allow": true,
    "canonical": false,
    "webz_reporter": false,
    "external_links": [
        "https://www.pacourts.us/assets/opinions/Supreme/out/J-44-2023mo%20-%20106154443288743161.pdf?cb=1",
        "https://www.inquirer.com/philly-tips/philadelphia-gun-laws-pennsylvania-firearm-preemption-law.html",
        "https://www.tribunecontentagency.com/",
        "https://www.inquirer.com/news/philadelphia-violence-gun-control-lawsuit-preemption-pennsylvania-20201007.html",
        "https://www.inquirer.com/philly/blogs/clout/BREAKING_State_Court_Says_City_Cant_Enact_Local_Gun_Laws.html",
        "https://pacourts.us/assets/opinions/Supreme/out/J-44-2023mo%20-%20106154443288743161.pdf?cb=1",
        "https://www.tribunecontentagency.com",
        "https://inquirer.com/philly/blogs/clout/BREAKING_State_Court_Says_City_Cant_Enact_Local_Gun_Laws.html",
        "https://inquirer.com/news/philadelphia-violence-gun-control-lawsuit-preemption-pennsylvania-20201007.html",
        "https://www.pacourts.us/assets/opinions/Supreme/out/J-44-2023mo%20-%20106154443288743161.pdf",
        "https://inquirer.com/philly-tips/philadelphia-gun-laws-pennsylvania-firearm-preemption-law.html",
        "https://tribunecontentagency.com/"
    ],
    "external_images": [],
    "entities": {
        "persons": [
            {
                "name": "Jim Kenney",
                "sentiment": "none"
            }
        ],
        "organizations": [
            {
                "name": "Pennsylvania Supreme Court",
                "sentiment": "negative"
            },
            {
                "name": "City Council",
                "sentiment": "none"
            }
        ],
        "locations": [
            {
                "name": "Philly",
                "sentiment": "none"
            }
        ]
    },
    "syndication": {
        "syndicated": false,
        "syndicate_id": null,
        "first_syndicated": false
    },
    "rating": null,
    "crawled": "2024-11-23T00:16:24.625+02:00",
    "updated": "2024-11-23T00:24:10.366+02:00"
}