{
    "thread": {
        "uuid": "891a556c3668d76db9bb28271c44871b3d9f61f9",
        "url": "https://time.news/2991270-2",
        "site_full": "time.news",
        "site": "time.news",
        "site_section": "https://www.time.news",
        "site_categories": [],
        "section_title": "TIme News - time.news",
        "title": "–",
        "title_full": "–",
        "published": "2024-11-22T23:51:00.000+02:00",
        "replies_count": 0,
        "participants_count": 1,
        "site_type": "news",
        "country": "US",
        "main_image": "",
        "performance_score": 0,
        "domain_rank": 70028,
        "domain_rank_updated": "2024-11-18T23:00:00.000+02:00",
        "social": {
            "facebook": {
                "likes": 0,
                "comments": 0,
                "shares": 0
            },
            "vk": {
                "shares": 0
            }
        }
    },
    "uuid": "891a556c3668d76db9bb28271c44871b3d9f61f9",
    "url": "https://time.news/2991270-2",
    "ord_in_thread": 0,
    "parent_url": null,
    "author": "times news cr",
    "published": "2024-11-22T23:51:00.000+02:00",
    "title": "–",
    "text": "The media published information about secret meetings between UNRWA and⁤ the leaders of ⁢Palestinian terrorist groups.\nThe former commissioner ⁣general of ‌the agency, Pierre Krahenbühl, held talks in Beirut in February ⁣2017 with​ representatives⁣ of the terrorist organizations Hamas, Islamic Jihad (PIJ), the Popular Front for the Liberation ⁢of⁣ Palestine (PFLP) and ‍others. The meeting was also attended by⁣ the head of⁢ UNRWA in Lebanon, ‌Hakam Shawan, as⁤ well as prominent leaders of terrorist organizations, including Ali Baraka and Abu Imad al-Rifai.\nAccording to the publication, Krahenbuhl sought to establish cooperation with these groups, saying⁢ that the agency and the militants must work as a “united front.” He urged meeting participants⁤ to refrain from publicly criticizing ‍UNRWA to avoid ‍backlash from donor ‌countries that could lead ⁣to cuts in ⁣funding ‍for ‌the agency.\nHamas terrorist leader Ali Barak, who handled the ‌organization’s foreign relations with Iran and Syria and later came⁢ under US sanctions, was one of the meeting participants. Abu⁤ Imad al-Rifai, ⁢who represents Islamic Jihad in Lebanon, has previously said his group sent suicide​ bombers to attack Western military personnel. The presence of such figures at the negotiations with UNRWA caused a‍ wide resonance.\nDocuments⁢ show that Krahenbühl openly discussed the possibility of changing or overturning UNRWA decisions at the request⁤ of terrorist‍ organizations. He emphasized the importance of a “spirit of⁤ partnership” and ⁣invited representatives of Hamas and ⁤other groups‍ to private discussions on controversial issues.\nUN Watch director Hillel Neuer noted⁣ that such contacts between UNRWA and Hamas were not ‍isolated. In particular, the agency’s regional directors not only met with militant leaders, but also congratulated them on their anniversaries of activity, despite the international recognition of Hamas as a terrorist organization.\nThis information became especially resonant after the events of October ‍7, when Hamas militants‍ committed massacres.\nIt⁢ is reported that some UNRWA personnel took part in Hamas activities by collaborating with al-Qassam. In addition, UNRWA-run schools were used ⁢to promote anti-Semitism and violence. One of the agency’s teachers was even seen organizing ⁤anti-Israeli protests in the Netherlands on⁣ behalf ⁤of a group associated⁣ with Hamas terrorists.\nEarlier, Kursor wrote that the pogrom in Amsterdam could‌ have been organized by an UNRWA teacher.‍\nNew results from the investigation into the pogrom in Amsterdam have emerged.\nHow can UNRWA restore its credibility after allegations‍ of compromised neutrality in middle eastern politics? Title: A Troubling Alliance: UNRWA and Palestinian Groups\nInterviewer (Time.news Editor): Good morning, and thank you for‌ joining us today. We have with us Dr. Sarah​ Lewis, ⁢an expert in Middle Eastern politics and humanitarian initiatives. Dr. Lewis, there’s been some alarming news regarding UNRWA’s past⁢ dealings with Palestinian militant groups. Can you help us unpack⁢ the implications of these ‍secret meetings?\nDr. Sarah Lewis: Good morning, and thank you for having me. Indeed, the revelations surrounding⁣ the meetings between former UNRWA commissioner Pierre Krahenbühl and ⁤leaders from groups like Hamas and Islamic Jihad are quite concerning. These meetings‌ raise​ significant questions about the integrity and neutrality of humanitarian organizations ‌in conflict zones.\nInterviewer: Absolutely. The report indicates that Krahenbühl sought to establish a “united front” with ⁣these groups. What do you think his motivations were?\nDr. Lewis: Krahenbühl likely believed that establishing cooperation could facilitate aid delivery ⁣and improve conditions for those affected by conflict. However, ​this approach ⁢can dangerously ⁤blur the lines between humanitarian action and political agendas. It’s vital for organizations like UNRWA to remain neutral, as their effectiveness ⁣relies heavily⁣ on‍ trust from all stakeholders, including donor countries.\nInterviewer: So, in seeking this cooperation, did⁤ Krahenbühl ‌potentially‍ jeopardize UNRWA’s credibility?\nDr. Lewis: Yes, he did. By aligning with such⁤ groups,‍ there’s an inherent risk of the agency being perceived as ‌complicit in their​ actions, which could provoke a backlash‌ from donor nations. Such backlash could lead to funding cuts, ultimately harming the very communities that UNRWA aims to support.\nInterviewer: You mentioned the potential consequences for donor relations. How significant ‍are these‍ funding streams for UNRWA, and what could this mean for their⁢ operations on ‍the ground?\nDr. Lewis: Funding is critically important for UNRWA, as⁢ it relies heavily‍ on international ‍donations to provide⁤ essential services like education, healthcare, and emergency assistance. A reduction‍ in funds could lead to ⁢cutbacks in these services, exacerbating the humanitarian‌ crisis already present in Palestinian ⁣territories. It⁢ could ⁤also⁤ lead to increased instability ⁤in ‍an⁢ already volatile region.\nInterviewer: These‌ discussions reportedly took place ‌in Beirut back in February 2017. Why⁤ do you think​ this information is coming to light now?\nDr. ⁢Lewis: The‌ timing ⁢of these revelations could be linked ⁢to ⁣growing scrutiny of humanitarian organizations and their relationships with militant groups. With the ongoing ​conflict ‌and shifting‌ political landscapes in the Middle East, stakeholders are increasingly being held accountable for their⁢ affiliations and actions. The media plays a crucial role in uncovering these ⁢relationships and prompting‍ necessary‍ discourse.\nInterviewer: What steps do you think UNRWA‌ should take moving forward to restore trust and maintain its operations effectively?\nDr. ⁣Lewis: First and foremost, transparency is key. UNRWA should conduct a thorough review of​ its policies and engage independent audits to ​reassure stakeholders that⁣ they operate ‍with integrity. They must reaffirm their commitment to neutrality and work diligently‌ to rebuild relationships with donor countries while ensuring that aid reaches those in need without political ​entanglements.\nInterviewer: Dr. ⁣Lewis, thank you for shedding light on these complex issues. It is ‍indeed a challenging time for humanitarian organizations ‌navigating the delicate balance between aid ‍and​ politics. We appreciate your insights.\nDr. Lewis: Thank you for having me. It’s crucial that we continue to discuss ​these issues comprehensively to ensure that humanitarian efforts⁤ remain ⁤focused‌ on those who need⁤ them‌ most.",
    "highlightText": "",
    "highlightTitle": "",
    "highlightThreadTitle": "",
    "language": "english",
    "sentiment": "negative",
    "categories": [
        "Politics",
        "War, Conflict and Unrest",
        "Social Issue"
    ],
    "ai_allow": true,
    "canonical": false,
    "webz_reporter": false,
    "external_links": [
        "https://www.youtube.com/embed/wiXhK7aEuGY",
        "https://youtube.com/embed/wiXhK7aEuGY"
    ],
    "external_images": [],
    "entities": {
        "persons": [],
        "organizations": [],
        "locations": []
    },
    "syndication": {
        "syndicated": false,
        "syndicate_id": null,
        "first_syndicated": false
    },
    "rating": null,
    "crawled": "2024-11-23T01:22:59.198+02:00",
    "updated": "2024-11-23T01:22:59.198+02:00"
}